medusa/__init__.py
medusa/__main__.py
medusa/cli.py
medusa/config.py
medusa/dependencies.json
medusa/setup_path.py
medusa/tool-versions.lock
medusa/core/__init__.py
medusa/core/fp_filter.py
medusa/core/parallel.py
medusa/core/pattern_analyzer.py
medusa/core/reporter.py
medusa/core/system.py
medusa/ide/__init__.py
medusa/ide/backup.py
medusa/ide/claude_code.py
medusa/platform/__init__.py
medusa/platform/detector.py
medusa/platform/install_manifest.py
medusa/platform/tool_cache.py
medusa/platform/version_manager.py
medusa/platform/installers/__init__.py
medusa/platform/installers/base.py
medusa/platform/installers/cross_platform.py
medusa/platform/installers/linux.py
medusa/platform/installers/macos.py
medusa/platform/installers/windows.py
medusa/platform/installers/windows_scripts/install-checkstyle.ps1
medusa/platform/installers/windows_scripts/install-clj-kondo.ps1
medusa/platform/installers/windows_scripts/install-ktlint.ps1
medusa/platform/installers/windows_scripts/install-phpstan.ps1
medusa/platform/installers/windows_scripts/install-taplo.ps1
medusa/platform/installers/windows_scripts/installer-versions.json
medusa/scanners/__init__.py
medusa/scanners/a2a_scanner.py
medusa/scanners/agent_memory_scanner.py
medusa/scanners/agent_planning_scanner.py
medusa/scanners/agent_reflection_scanner.py
medusa/scanners/ai_context_scanner.py
medusa/scanners/ansible_scanner.py
medusa/scanners/base.py
medusa/scanners/bash_scanner.py
medusa/scanners/bat_scanner.py
medusa/scanners/clojure_scanner.py
medusa/scanners/cmake_scanner.py
medusa/scanners/cpp_scanner.py
medusa/scanners/css_scanner.py
medusa/scanners/dart_scanner.py
medusa/scanners/docker_compose_scanner.py
medusa/scanners/docker_mcp_scanner.py
medusa/scanners/docker_scanner.py
medusa/scanners/elixir_scanner.py
medusa/scanners/env_scanner.py
medusa/scanners/excessive_agency_scanner.py
medusa/scanners/garak_scanner.py
medusa/scanners/gitleaks_scanner.py
medusa/scanners/go_scanner.py
medusa/scanners/graphql_scanner.py
medusa_security-2025.9.1.1.dist-info/licenses/LICENSE
medusa_security-2025.9.1.1.dist-info/METADATA
medusa_security-2025.9.1.1.dist-info/WHEEL
medusa_security-2025.9.1.1.dist-info/entry_points.txt
medusa_security-2025.9.1.1.dist-info/top_level.txt
medusa_security-2025.9.1.1.dist-info/RECORD
