Metadata-Version: 2.4
Name: medusa-security
Version: 2025.9.1.1
Summary: AI-first security scanner with 74 analyzers, intelligent false positive reduction, and 180+ AI agent security rules
Author-email: Pantheon Security <support@pantheonsecurity.io>
Maintainer-email: Pantheon Security <support@pantheonsecurity.io>
License: AGPL-3.0-or-later
Project-URL: Homepage, https://pantheonsecurity.io
Project-URL: Documentation, https://docs.pantheonsecurity.io
Project-URL: Repository, https://github.com/pantheon-security/medusa
Project-URL: Bug Tracker, https://github.com/pantheon-security/medusa/issues
Keywords: security,scanner,sast,ai-security,llm-security,mcp,agent-security,prompt-injection,false-positive-reduction,rag-security,cybersecurity,devsecops
Classifier: Development Status :: 4 - Beta
Classifier: Intended Audience :: Developers
Classifier: Topic :: Security
Classifier: Topic :: Software Development :: Quality Assurance
Classifier: License :: OSI Approved :: GNU Affero General Public License v3 or later (AGPLv3+)
Classifier: Programming Language :: Python :: 3
Classifier: Programming Language :: Python :: 3.10
Classifier: Programming Language :: Python :: 3.11
Classifier: Programming Language :: Python :: 3.12
Classifier: Operating System :: OS Independent
Classifier: Environment :: Console
Requires-Python: >=3.10
License-File: LICENSE
Requires-Dist: click>=8.1.0
Requires-Dist: rich>=13.0.0
Requires-Dist: bandit>=1.9.0
Requires-Dist: yamllint>=1.28.0
Requires-Dist: tqdm>=4.60.0
Requires-Dist: requests>=2.28.0
Requires-Dist: urllib3>=2.6.0
Requires-Dist: pyyaml>=6.0.0
Requires-Dist: psutil>=5.9.0
Requires-Dist: defusedxml>=0.7.0
Requires-Dist: tomli-w>=1.0.0
Requires-Dist: toml>=0.10.2
Requires-Dist: Blinter>=1.0.0
Provides-Extra: dev
Requires-Dist: pytest>=7.0.0; extra == "dev"
Requires-Dist: pytest-cov>=4.0.0; extra == "dev"
Requires-Dist: black>=23.0.0; extra == "dev"
Requires-Dist: ruff>=0.1.0; extra == "dev"
Requires-Dist: mypy>=1.0.0; extra == "dev"
Provides-Extra: docs
Requires-Dist: mkdocs>=1.5.0; extra == "docs"
Requires-Dist: mkdocs-material>=9.0.0; extra == "docs"
Dynamic: license-file
